LICENSE
MANIFEST.in
README.rst
setup.py
django_media_tools.egg-info/PKG-INFO
django_media_tools.egg-info/SOURCES.txt
django_media_tools.egg-info/dependency_links.txt
django_media_tools.egg-info/top_level.txt
media_tools/__init__.py
media_tools/apps.py
media_tools/widgets.py
media_tools/static/media_tools/css/image-preview-widget.css
media_tools/static/media_tools/js/image-preview-widget.js
media_tools/templates/media_tools/image-preview-widget.html