Metadata-Version: 1.1
Name: django-media-tools
Version: 0.1.0
Summary: A Django app that provides widgets for media files
Home-page: https://github.com/zeyneloz/django-media-tools
Author: Zeynel
Author-email: UNKNOWN
License: MIT License
Platform: UNKNOWN
Classifier: Environment :: Web Environment
Classifier: Framework :: Django
Classifier: Intended Audience :: Developers
Classifier: License :: OSI Approved :: MIT License
Classifier: Operating System :: OS Independent
Classifier: Programming Language :: Python
Classifier: Programming Language :: Python :: 3
Classifier: Programming Language :: Python :: 3.6
